{"cameraMode":{"drawMode":0,"name":"Shaded","section":"Shading Mode"},"sceneLighting":true,"audioPlay":false,"sceneViewState":{"m_AlwaysRefresh":false,"showFog":true,"showSkybox":true,"showFlares":true,"showImageEffects":true,"showParticleSystems":true,"showVisualEffectGraphs":true,"m_FxEnabled":true},"in2DMode":false,"pivot":{"x":3.663829803466797,"y":-4.197663307189941,"z":15.943659782409668},"rotation":{"x":-0.2344239354133606,"y":0.4694809913635254,"z":-0.13084441423416139,"w":-0.8411031365394592},"size":13.879257202148438,"orthographic":false}